{
  "custom_clouds": true,
  "custom_sky": true,
  "custom_weather": false,
  "dimension": "ad_astra:extendra_haumea",
  "has_fog": false,
  "has_thick_fog": false,
  "render_in_rain": true,
  "sky_renderables": [
    {
      "back_light_color": -39,
      "back_light_scale": 0.57,
      "blend": false,
      "global_rotation": [
        0.0,
        0.0,
        0.0
      ],
      "local_rotation": [
        0.0,
        0.0,
        0.0
      ],
      "movement_type": "TIME_OF_DAY",
      "scale": 0.19,
      "texture": "ad_astra:textures/environment/sun.png"
    },
    {
      "back_light_color": 4408131,
      "back_light_scale": 1.86,
      "blend": true,
      "global_rotation": [
        0.0,
        10.0,
        180.0
      ],
      "local_rotation": [
        0.0,
        0.0,
        0.0
      ],
      "movement_type": "TIME_OF_DAY_REVERSED",
      "scale": 0.62,
      "texture": "ad_astra:textures/environment/hiiaka.png"
    },
    {
      "back_light_color": 5658198,
      "back_light_scale": 1.02,
      "blend": true,
      "global_rotation": [
        0.0,
        -10.0,
        180.0
      ],
      "local_rotation": [
        0.0,
        0.0,
        0.0
      ],
      "movement_type": "TIME_OF_DAY_REVERSED",
      "scale": 0.34,
      "texture": "ad_astra:textures/environment/namaka.png"
    }
  ],
  "star_colors": [
    {
      "data": -1,
      "weight": 1
    }
  ],
  "stars": 1500,
  "sunrise_angle": 0,
  "sunrise_color": 5460819
}